{"stats":{"minecraft:crafted":{"minecraft:emerald":3},"minecraft:dropped":{"minecraft:iron_ingot":1,"minecraft:baked_potato":1},"minecraft:killed_by":{"minecraft:player":1},"minecraft:used":{"minecraft:baked_potato":1,"minecraft:iron_helmet":1,"minecraft:iron_boots":1,"minecraft:netherrack":13,"minecraft:sand":2,"minecraft:carrot":10},"minecraft:picked_up":{"minecraft:stick":10,"minecraft:iron_chestplate":2,"minecraft:golden_carrot":30,"minecraft:sand":1,"minecraft:carrot":41,"minecraft:iron_leggings":2,"minecraft:arrow":1,"minecraft:iron_helmet":3,"minecraft:iron_ingot":18,"minecraft:emerald":3,"minecraft:baked_potato":10,"minecraft:netherrack":85,"minecraft:iron_boots":3},"minecraft:mined":{"minecraft:carrots":9,"minecraft:torch":1,"minecraft:sand":1,"minecraft:sugar_cane":2},"minecraft:custom":{"minecraft:time_since_rest":3958,"minecraft:sprint_one_cm":37105,"minecraft:damage_taken":808,"minecraft:walk_one_cm":40172,"minecraft:drop":2,"minecraft:inspect_hopper":1,"minecraft:damage_dealt":211,"minecraft:traded_with_villager":3,"minecraft:swim_one_cm":4232,"minecraft:talked_to_villager":3,"minecraft:fly_one_cm":31226,"minecraft:open_chest":26,"minecraft:crouch_one_cm":1665,"minecraft:play_time":17189,"minecraft:deaths":1,"minecraft:sneak_time":401,"minecraft:walk_under_water_one_cm":2804,"minecraft:jump":220,"minecraft:leave_game":1,"minecraft:walk_on_water_one_cm":1921,"minecraft:time_since_death":3926,"minecraft:climb_one_cm":2179,"minecraft:total_world_time":17189,"minecraft:fall_one_cm":6004}},"DataVersion":4082}